intake_axds/__init__.py
intake_axds/_version.py
intake_axds/axds.py
intake_axds/axds_cat.py
intake_axds/utils.py
intake_axds-0.4.0.dist-info/LICENSE.txt
intake_axds-0.4.0.dist-info/METADATA
intake_axds-0.4.0.dist-info/WHEEL
intake_axds-0.4.0.dist-info/entry_points.txt
intake_axds-0.4.0.dist-info/top_level.txt
intake_axds-0.4.0.dist-info/RECORD
