Metadata-Version: 2.1
Name: intake-axds
Version: 0.4.0
Summary: Intake interface to Axiom assets
Home-page: https://github.com/axiom-data-science/intake-axds
Author: Axiom Data Science
Author-email: dev@axds.co
License: MIT
Classifier: Development Status :: 5 - Production/Stable
Classifier: Topic :: Scientific/Engineering
Classifier: Intended Audience :: Science/Research
Classifier: Operating System :: OS Independent
Classifier: Programming Language :: Python
Classifier: Programming Language :: Python :: 3
Classifier: Programming Language :: Python :: 3.8
Classifier: Programming Language :: Python :: 3.9
Classifier: Programming Language :: Python :: 3.10
Classifier: License :: OSI Approved :: MIT License
Requires-Python: >=3.8
License-File: LICENSE.txt
Requires-Dist: cf-pandas
Requires-Dist: intake
Requires-Dist: intake-parquet
Requires-Dist: intake-xarray
Requires-Dist: pandas
Requires-Dist: requests
Requires-Dist: shapely
